freeplay/__init__.py
freeplay/api_support.py
freeplay/errors.py
freeplay/freeplay.py
freeplay/freeplay_cli.py
freeplay/llm_parameters.py
freeplay/model.py
freeplay/py.typed
freeplay/support.py
freeplay/utils.py
freeplay/resources/__init__.py
freeplay/resources/adapters.py
freeplay/resources/customer_feedback.py
freeplay/resources/metadata.py
freeplay/resources/prompts.py
freeplay/resources/recordings.py
freeplay/resources/sessions.py
freeplay/resources/test_cases.py
freeplay/resources/test_runs.py
freeplay-0.5.6.dist-info/METADATA
freeplay-0.5.6.dist-info/WHEEL
freeplay-0.5.6.dist-info/entry_points.txt
freeplay-0.5.6.dist-info/licenses/LICENSE
freeplay-0.5.6.dist-info/RECORD
