Metadata-Version: 2.4
Name: freeplay
Version: 0.5.6
Author-email: Freeplay Engineering <support@freeplay.ai>
License: Apache-2.0
License-File: LICENSE
Requires-Python: >=3.8
Requires-Dist: click<9.0.0,>=8.1.7
Requires-Dist: dacite<2.0.0,>=1.8.0
Requires-Dist: pystache<1.0.0,>=0.6.5
Requires-Dist: requests<3.0.0dev,>=2.20.0
